pylemur/__init__.py
pylemur/pl/__init__.py
pylemur/pl/basic.py
pylemur/pp/__init__.py
pylemur/pp/basic.py
pylemur/tl/__init__.py
pylemur/tl/_design_matrix_utils.py
pylemur/tl/_grassmann.py
pylemur/tl/_grassmann_lm.py
pylemur/tl/_lin_alg_wrappers.py
pylemur/tl/alignment.py
pylemur/tl/lemur.py
pylemur-0.3.1.dist-info/METADATA
pylemur-0.3.1.dist-info/WHEEL
pylemur-0.3.1.dist-info/licenses/LICENSE
pylemur-0.3.1.dist-info/RECORD
