Metadata-Version: 2.3
Name: pyLemur
Version: 0.3.1
Summary: A Python implementation of the LEMUR algorithm for analyzing multi-condition single-cell RNA-seq data.
Project-URL: Documentation, https://pyLemur.readthedocs.io/
Project-URL: Source, https://github.com/const-ae/pyLemur
Project-URL: Home-page, https://github.com/const-ae/pyLemur
Author: Constantin Ahlmann-Eltze
Maintainer-email: Constantin Ahlmann-Eltze <artjom31415@googlemail.com>
License: MIT License
Requires-Python: >=3.10
Requires-Dist: anndata
Requires-Dist: formulaic
Requires-Dist: formulaic-contrasts
Requires-Dist: harmonypy
Requires-Dist: numpy
Requires-Dist: pandas
Requires-Dist: scikit-learn
Requires-Dist: session-info
Provides-Extra: dev
Requires-Dist: pre-commit; extra == 'dev'
Requires-Dist: twine>=4.0.2; extra == 'dev'
Provides-Extra: doc
Requires-Dist: docutils!=0.18.*,!=0.19.*,>=0.8; extra == 'doc'
Requires-Dist: ipykernel; extra == 'doc'
Requires-Dist: ipython; extra == 'doc'
Requires-Dist: matplotlib; extra == 'doc'
Requires-Dist: myst-nb>=1.1.0; extra == 'doc'
Requires-Dist: pandas; extra == 'doc'
Requires-Dist: pertpy; extra == 'doc'
Requires-Dist: scanpy; extra == 'doc'
Requires-Dist: session-info; extra == 'doc'
Requires-Dist: sphinx-autodoc-typehints; extra == 'doc'
Requires-Dist: sphinx-book-theme>=1.0.0; extra == 'doc'
Requires-Dist: sphinx-copybutton; extra == 'doc'
Requires-Dist: sphinx-design; extra == 'doc'
Requires-Dist: sphinx>=4; extra == 'doc'
Requires-Dist: sphinxcontrib-bibtex>=1.0.0; extra == 'doc'
Requires-Dist: sphinxext-opengraph; extra == 'doc'
Provides-Extra: test
Requires-Dist: coverage; extra == 'test'
Requires-Dist: pytest; extra == 'test'
